Metadata-Version: 1.0
Name: abitfrosty
Version: 0.1
Summary: Gaussian and binomial distributions. Test package.
Home-page: UNKNOWN
Author: abitfrosty
Author-email: abitfrosty@gmail.com
License: UNKNOWN
Platform: UNKNOWN
